audiozen/__init__.py
audiozen/accelerate.py
audiozen/constant.py
audiozen/debug_utils.py
audiozen/logger.py
audiozen/loss.py
audiozen/lr_scheduler.py
audiozen/metric.py
audiozen/optimization.py
audiozen/pit.py
audiozen/trainer.py
audiozen/trainer_args.py
audiozen/trainer_callback.py
audiozen/trainer_naive.py
audiozen/trainer_naive_debug.py
audiozen/trainer_utils.py
audiozen/trainer_v2.py
audiozen/trainer_v2_hydra.py
audiozen/utils.py
audiozen/acoustics/__init__.py
audiozen/acoustics/audio_feature.py
audiozen/acoustics/femto.py
audiozen/acoustics/filterbank.py
audiozen/acoustics/hearing_loss.py
audiozen/acoustics/io.py
audiozen/acoustics/sslt.py
audiozen/acoustics/wdrc.py
audiozen/dataset/__init__.py
audiozen/dataset/base_dataset.py
audiozen/dataset/dns_interspeech_2020.py
audiozen/dataset/naive_noisy.py
audiozen/dataset/naive_paired_noisy_clean.py
audiozen/dataset/voicebank_demand.py
audiozen/evaluator/__init__.py
audiozen/evaluator/dnsmos/__init__.py
audiozen/evaluator/dnsmos/dnsmos.py
audiozen/evaluator/haspi/__init__.py
audiozen/evaluator/haspi/eb.py
audiozen/evaluator/haspi/ebm.py
audiozen/evaluator/haspi/haspi.py
audiozen/evaluator/haspi/ip.py
audiozen/evaluator/hasqi/__init__.py
audiozen/evaluator/hasqi/hasqi.py
audiozen/evaluator/stoi/__init__.py
audiozen/external/DNSMOS/bak_ovr.onnx
audiozen/external/DNSMOS/model_v8.onnx
audiozen/external/DNSMOS/sig.onnx
audiozen/external/DNSMOS/sig_bak_ovr.onnx
audiozen/external/pDNSMOS/sig_bak_ovr.onnx
audiozen/integrations/huggingface_hub.py
audiozen/metrics/__init__.py
audiozen/metrics/dns_mos.py
audiozen/metrics/metric_utils.py
audiozen/metrics/sxr.py
audiozen/models/__init__.py
audiozen/models/base_model.py
audiozen/models/fullsubnet.py
audiozen/models/bsrnn/configuration_mono_bsrnn.py
audiozen/models/bsrnn/modeling_mono_bsrnn.py
audiozen/models/cirm_gsn/modeling_cirm_gsn.py
audiozen/models/cirm_lstm/modeling_cirm_lstm.py
audiozen/models/conv_tasnet/modeling_conv_tasnet.py
audiozen-2025.11.17.dist-info/WHEEL
audiozen-2025.11.17.dist-info/METADATA
audiozen-2025.11.17.dist-info/RECORD
