Metadata-Version: 2.4
Name: audiozen
Version: 2025.11.17
Summary: Audio ZEN is a library for audio/speech signal processing.
Requires-Python: >=3.12
Requires-Dist: einops
Requires-Dist: librosa
Requires-Dist: simple_parsing
Requires-Dist: torchinfo
Requires-Dist: pyyaml
Requires-Dist: numpy
Requires-Dist: rich
Requires-Dist: numba>=0.60
Requires-Dist: ipykernel
Requires-Dist: tqdm
Requires-Dist: pandas
Requires-Dist: tabulate
Requires-Dist: matplotlib
Requires-Dist: joblib
Requires-Dist: psutil
Requires-Dist: torch==2.5.1
Requires-Dist: torchaudio
Requires-Dist: pesq>=0.0.4
Requires-Dist: pystoi>=0.4.1
Requires-Dist: deprecated>=1.2.18
Requires-Dist: tensorboard>=2.19.0
Requires-Dist: colorlog>=6.9.0
Requires-Dist: omegaconf>=2.3.0
Requires-Dist: pyloudnorm>=0.1.1
Requires-Dist: silero-vad>=6.0.0
Requires-Dist: onnxruntime-gpu==1.20
